{
    "msu_vis_1": {
        "1": {
            "type": 1
        },
        "2": {
            "ax": 0.9997,
            "ay": 1.0,
            "bx": -9.0,
            "by": -3575.0,
            "slantx_ampli": -0.0074,
            "slantx_center": 6002.0,
            "type": 3
        },
        "3": {
            "type": 1
        }
    },
    "msu_vis_2": {
        "1": {
            "type": 1
        },
        "2": {
            "type": 1
        },
        "3": {
            "type": 1
        }
    }
}